{
	"Aster": [
		"SICAT, ROME",
		"CANETE, PERLITA",
		"VIRAY, HELEN",
		"VILLANUEVA, EDNA",
		"BATUNGBAKAL, JOEL",
		"CRUZ, DENNIS",
		"FELICIANO, LILY",
		"BALBA, REZZA",
		"LIMPIN, BOY",
		"PADACA, REY",
		"CRUZ, RONALDO",
		"CASTILLO, NESTOR",
		"ENDIAFE, MANUEL",
		"EUGENIO, JOY",
		"OLETE, ROLANDO",
		"ESPIRITU, NERIE",
		"MANALILI, RUBEN"
	],
	"Gladiola": [
		"HONOR, CRISTY",
		"LINTAG, BETH",
		"SALANSANG, ZENGEL",
		"TOLEDO, HEIDY"
	],
	"Howthorne": [
		"ENRIQUEZ, JULITA",
		"SANTOS, LUIS",
		"ALMAZAN, JOSIE",
		"MURAMOTO, JOVY",
		"YUMANG, MICHELLE",
		"SANTOS, TERESA",
		"ANCHETA, CLAUDINE",
		"SIOSON, LYNNE",
		"TAMAYO, JAYSON",
		"PELAYO, ANGELITA",
		"TUMANG, RENE"
	],
	"Iris": [
		"JAVIER, LEONIDA",
		"CRUZ, NORA",
		"ANTONIO, FE",
		"PLATERO, DANNY",
		"MANABAT, LORETA",
		"BRIONES, ALEX",
		"JAVIER, EDGAR",
		"VIANZON, MICHAEL",
		"YUZON, CHARLIE",
		"ELLWOOD, GRACE",
		"NABUA, ANNE"
	],
	"Larkspur": [
		"TRINIDAD, NELFA",
		"RODRIGUEZ, RESMA",
		"GONZAGA, BERNADETTE",
		"DIZON, NERISSA",
		"DE LEON, FERLIZA",
		"SIGARANG, RHODORA",
		"SALAZAR, PRECY",
		"CALMA, ROMEO",
		"LAMBOLOTO, ROBERT",
		"ARIOLA, ALFREDO",
		"ASUNCION, ROMEO",
		"MINA, CECILLE"
	],
	"Narcissus": [
		"GABUCO, RUDY",
		"CURA, NELSON",
		"ROQUE, RONA",
		"LESCANO, ZENAIDA",
		"MEDINA, VOLTAIRE",
		"EUGENIO, BOYET",
		"VIERNEZ, JENNIE",
		"MAYOR, ANNIE",
		"MICOR, MARISSA",
		"CASTANEDA, DORIS"
	],
	"Marigold": [
		"BUGAY, IRISH",
		"SENORESES, VERONICA",
		"DUCUT, MARY ANN",
		"MINA, RIZZA",
		"MINA, EDYLE",
		"SANCHEZ, HAZE",
		"MANGROBANG, LITO",
		"SEVILLA, MICHAEL"
	],
	"Primrose": [
		"TOLENTINO, CRISTY",
		"REYES, RUBEN",
		"MORALES, DANILO"
	]
}
